mlrun/__init__.py
mlrun/__main__.py
mlrun/config.py
mlrun/errors.py
mlrun/execution.py
mlrun/features.py
mlrun/k8s_utils.py
mlrun/lists.py
mlrun/model.py
mlrun/render.py
mlrun/run.py
mlrun/secrets.py
mlrun/alerts/__init__.py
mlrun/alerts/alert.py
mlrun/api/schemas/__init__.py
mlrun/artifacts/__init__.py
mlrun/artifacts/base.py
mlrun/artifacts/dataset.py
mlrun/artifacts/document.py
mlrun/artifacts/manager.py
mlrun/artifacts/model.py
mlrun/artifacts/plots.py
mlrun/common/__init__.py
mlrun/common/constants.py
mlrun/common/helpers.py
mlrun/common/secrets.py
mlrun/common/types.py
mlrun/common/db/__init__.py
mlrun/common/db/sql_session.py
mlrun/common/formatters/__init__.py
mlrun/common/formatters/artifact.py
mlrun/common/formatters/base.py
mlrun/common/formatters/feature_set.py
mlrun/common/formatters/function.py
mlrun/common/formatters/model_endpoint.py
mlrun/common/formatters/pipeline.py
mlrun/common/formatters/project.py
mlrun/common/formatters/run.py
mlrun/common/model_monitoring/__init__.py
mlrun/common/model_monitoring/helpers.py
mlrun/common/runtimes/constants.py
mlrun/common/schemas/__init__.py
mlrun/common/schemas/alert.py
mlrun/common/schemas/api_gateway.py
mlrun/common/schemas/artifact.py
mlrun/common/schemas/auth.py
mlrun/common/schemas/background_task.py
mlrun/common/schemas/client_spec.py
mlrun/common/schemas/clusterization_spec.py
mlrun/common/schemas/common.py
mlrun/common/schemas/constants.py
mlrun/common/schemas/datastore_profile.py
mlrun/common/schemas/events.py
mlrun/common/schemas/feature_store.py
mlrun/common/schemas/frontend_spec.py
mlrun/common/schemas/function.py
mlrun/common/schemas/http.py
mlrun/common/schemas/hub.py
mlrun/common/schemas/k8s.py
mlrun/common/schemas/memory_reports.py
mlrun/common/schemas/notification.py
mlrun/common/schemas/object.py
mlrun/common/schemas/pagination.py
mlrun/common/schemas/partition.py
mlrun/common/schemas/pipeline.py
mlrun/common/schemas/project.py
mlrun/common/schemas/regex.py
mlrun/common/schemas/runs.py
mlrun-1.9.2.dist-info/licenses/LICENSE
mlrun-1.9.2.dist-info/METADATA
mlrun-1.9.2.dist-info/WHEEL
mlrun-1.9.2.dist-info/entry_points.txt
mlrun-1.9.2.dist-info/top_level.txt
mlrun-1.9.2.dist-info/RECORD
