Metadata-Version: 2.4
Name: mlrun
Version: 1.9.2
Summary: Tracking and config of machine learning runs
Home-page: https://github.com/mlrun/mlrun
Author: Yaron Haviv
Author-email: yaronh@iguazio.com
License: Apache License 2.0
Keywords: mlrun,mlops,data-science,machine-learning,experiment-tracking
Classifier: Development Status :: 4 - Beta
Classifier: Intended Audience :: Developers
Classifier: License :: OSI Approved :: Apache Software License
Classifier: Operating System :: POSIX :: Linux
Classifier: Operating System :: Microsoft :: Windows
Classifier: Operating System :: MacOS
Classifier: Programming Language :: Python :: 3
Classifier: Programming Language :: Python :: 3.9
Classifier: Programming Language :: Python :: 3.11
Classifier: Programming Language :: Python
Classifier: Topic :: Software Development :: Libraries :: Python Modules
Classifier: Topic :: Software Development :: Libraries
Requires-Python: >=3.9, <3.12
License-File: LICENSE
Requires-Dist: urllib3<1.27,>=1.26.9
Requires-Dist: GitPython>=3.1.41,~=3.1
Requires-Dist: aiohttp~=3.11
Requires-Dist: aiohttp-retry~=2.9
Requires-Dist: click~=8.1
Requires-Dist: nest-asyncio~=1.0
Requires-Dist: ipython~=8.10
Requires-Dist: nuclio-jupyter~=0.11.1
Requires-Dist: numpy<1.27.0,>=1.26.4
Requires-Dist: pandas<2.2,>=1.2
Requires-Dist: pyarrow<18,>=10.0
Requires-Dist: pyyaml<7,>=6.0.2
Requires-Dist: requests~=2.32
Requires-Dist: tabulate~=0.8.6
Requires-Dist: v3io~=0.7.0
Requires-Dist: pydantic>=1.10.15
Requires-Dist: mergedeep~=1.3
Requires-Dist: v3io-frames~=0.10.14; python_version < "3.11"
Requires-Dist: v3io-frames>=0.13.0; python_version >= "3.11"
Requires-Dist: semver~=3.0
Requires-Dist: dependency-injector~=4.41
Requires-Dist: fsspec<2024.7,>=2023.9.2
Requires-Dist: v3iofs~=0.1.17
Requires-Dist: storey~=1.9.0
Requires-Dist: inflection~=0.5.0
Requires-Dist: python-dotenv~=1.0
Requires-Dist: setuptools>=75.2
Requires-Dist: deprecated~=1.2
Requires-Dist: jinja2>=3.1.3,~=3.1
Requires-Dist: orjson<4,>=3.9.15
Requires-Dist: mlrun-pipelines-kfp-common~=0.4.4
Requires-Dist: mlrun-pipelines-kfp-v1-8~=0.4.3
Requires-Dist: docstring_parser~=0.16
Requires-Dist: aiosmtplib~=3.0
Provides-Extra: s3
Requires-Dist: boto3<1.36,>=1.28.0; extra == "s3"
Requires-Dist: aiobotocore<2.16,>=2.5.0; extra == "s3"
Requires-Dist: s3fs<2024.7,>=2023.9.2; extra == "s3"
Provides-Extra: azure-blob-storage
Requires-Dist: msrest~=0.6.21; extra == "azure-blob-storage"
Requires-Dist: azure-core~=1.24; extra == "azure-blob-storage"
Requires-Dist: adlfs==2023.9.0; extra == "azure-blob-storage"
Requires-Dist: pyopenssl>=23; extra == "azure-blob-storage"
Provides-Extra: azure-key-vault
Requires-Dist: azure-identity~=1.5; extra == "azure-key-vault"
Requires-Dist: azure-keyvault-secrets~=4.2; extra == "azure-key-vault"
Requires-Dist: pyopenssl>=23; extra == "azure-key-vault"
Provides-Extra: plotly
Requires-Dist: plotly~=5.23; extra == "plotly"
Provides-Extra: graphviz
Requires-Dist: graphviz~=0.20.0; extra == "graphviz"
Provides-Extra: google-cloud
Requires-Dist: google-cloud-storage==2.14.0; extra == "google-cloud"
Requires-Dist: google-cloud-bigquery[bqstorage,pandas]==3.14.1; extra == "google-cloud"
Requires-Dist: google-cloud-bigquery-storage~=2.17; extra == "google-cloud"
Requires-Dist: google-cloud==0.34; extra == "google-cloud"
Requires-Dist: gcsfs<2024.7,>=2023.9.2; extra == "google-cloud"
Provides-Extra: kafka
Requires-Dist: kafka-python~=2.1.0; extra == "kafka"
Requires-Dist: avro~=1.11; extra == "kafka"
Provides-Extra: redis
Requires-Dist: redis~=4.3; extra == "redis"
Provides-Extra: mlflow
Requires-Dist: mlflow~=2.16; extra == "mlflow"
Provides-Extra: databricks-sdk
Requires-Dist: databricks-sdk~=0.20.0; extra == "databricks-sdk"
Provides-Extra: sqlalchemy
Requires-Dist: sqlalchemy~=1.4; extra == "sqlalchemy"
Provides-Extra: dask
Requires-Dist: dask~=2024.12.1; python_version >= "3.11" and extra == "dask"
Requires-Dist: distributed~=2024.12.1; python_version >= "3.11" and extra == "dask"
Requires-Dist: dask~=2023.12.1; python_version < "3.11" and extra == "dask"
Requires-Dist: distributed~=2023.12.1; python_version < "3.11" and extra == "dask"
Provides-Extra: alibaba-oss
Requires-Dist: ossfs==2023.12.0; extra == "alibaba-oss"
Requires-Dist: oss2==2.18.1; extra == "alibaba-oss"
Provides-Extra: tdengine
Requires-Dist: taos-ws-py==0.3.2; extra == "tdengine"
Provides-Extra: snowflake
Requires-Dist: snowflake-connector-python~=3.7; extra == "snowflake"
Provides-Extra: kfp18
Requires-Dist: mlrun_pipelines_kfp_v1_8[kfp]>=0.4.0; python_version < "3.11" and extra == "kfp18"
Provides-Extra: api
Requires-Dist: uvicorn~=0.32.1; extra == "api"
Requires-Dist: dask-kubernetes~=0.11.0; extra == "api"
Requires-Dist: apscheduler<4,>=3.11; extra == "api"
Requires-Dist: objgraph~=3.6; extra == "api"
Requires-Dist: igz-mgmt~=0.4.1; extra == "api"
Requires-Dist: humanfriendly~=10.0; extra == "api"
Requires-Dist: fastapi~=0.115.6; extra == "api"
Requires-Dist: sqlalchemy~=1.4; extra == "api"
Requires-Dist: pymysql~=1.1; extra == "api"
Requires-Dist: alembic~=1.14; extra == "api"
Requires-Dist: timelength~=1.1; extra == "api"
Requires-Dist: memray~=1.12; sys_platform != "win32" and extra == "api"
Requires-Dist: aiosmtplib~=3.0; extra == "api"
Requires-Dist: pydantic<2,>=1; extra == "api"
Requires-Dist: mlrun-pipelines-kfp-v1-8~=0.4.3; extra == "api"
Requires-Dist: grpcio~=1.70.0; extra == "api"
Provides-Extra: all
Requires-Dist: adlfs==2023.9.0; extra == "all"
Requires-Dist: aiobotocore<2.16,>=2.5.0; extra == "all"
Requires-Dist: avro~=1.11; extra == "all"
Requires-Dist: azure-core~=1.24; extra == "all"
Requires-Dist: azure-identity~=1.5; extra == "all"
Requires-Dist: azure-keyvault-secrets~=4.2; extra == "all"
Requires-Dist: boto3<1.36,>=1.28.0; extra == "all"
Requires-Dist: dask~=2023.12.1; python_version < "3.11" and extra == "all"
Requires-Dist: dask~=2024.12.1; python_version >= "3.11" and extra == "all"
Requires-Dist: databricks-sdk~=0.20.0; extra == "all"
Requires-Dist: distributed~=2023.12.1; python_version < "3.11" and extra == "all"
Requires-Dist: distributed~=2024.12.1; python_version >= "3.11" and extra == "all"
Requires-Dist: gcsfs<2024.7,>=2023.9.2; extra == "all"
Requires-Dist: google-cloud-bigquery-storage~=2.17; extra == "all"
Requires-Dist: google-cloud-bigquery[bqstorage,pandas]==3.14.1; extra == "all"
Requires-Dist: google-cloud-storage==2.14.0; extra == "all"
Requires-Dist: google-cloud==0.34; extra == "all"
Requires-Dist: graphviz~=0.20.0; extra == "all"
Requires-Dist: kafka-python~=2.1.0; extra == "all"
Requires-Dist: mlflow~=2.16; extra == "all"
Requires-Dist: msrest~=0.6.21; extra == "all"
Requires-Dist: oss2==2.18.1; extra == "all"
Requires-Dist: ossfs==2023.12.0; extra == "all"
Requires-Dist: plotly~=5.23; extra == "all"
Requires-Dist: pyopenssl>=23; extra == "all"
Requires-Dist: redis~=4.3; extra == "all"
Requires-Dist: s3fs<2024.7,>=2023.9.2; extra == "all"
Requires-Dist: snowflake-connector-python~=3.7; extra == "all"
Requires-Dist: sqlalchemy~=1.4; extra == "all"
Requires-Dist: taos-ws-py==0.3.2; extra == "all"
Provides-Extra: complete
Requires-Dist: adlfs==2023.9.0; extra == "complete"
Requires-Dist: aiobotocore<2.16,>=2.5.0; extra == "complete"
Requires-Dist: avro~=1.11; extra == "complete"
Requires-Dist: azure-core~=1.24; extra == "complete"
Requires-Dist: azure-identity~=1.5; extra == "complete"
Requires-Dist: azure-keyvault-secrets~=4.2; extra == "complete"
Requires-Dist: boto3<1.36,>=1.28.0; extra == "complete"
Requires-Dist: dask~=2023.12.1; python_version < "3.11" and extra == "complete"
Requires-Dist: dask~=2024.12.1; python_version >= "3.11" and extra == "complete"
Requires-Dist: databricks-sdk~=0.20.0; extra == "complete"
Requires-Dist: distributed~=2023.12.1; python_version < "3.11" and extra == "complete"
Requires-Dist: distributed~=2024.12.1; python_version >= "3.11" and extra == "complete"
Requires-Dist: gcsfs<2024.7,>=2023.9.2; extra == "complete"
Requires-Dist: google-cloud-bigquery-storage~=2.17; extra == "complete"
Requires-Dist: google-cloud-bigquery[bqstorage,pandas]==3.14.1; extra == "complete"
Requires-Dist: google-cloud-storage==2.14.0; extra == "complete"
Requires-Dist: google-cloud==0.34; extra == "complete"
Requires-Dist: graphviz~=0.20.0; extra == "complete"
Requires-Dist: kafka-python~=2.1.0; extra == "complete"
Requires-Dist: mlflow~=2.16; extra == "complete"
Requires-Dist: msrest~=0.6.21; extra == "complete"
Requires-Dist: oss2==2.18.1; extra == "complete"
Requires-Dist: ossfs==2023.12.0; extra == "complete"
Requires-Dist: plotly~=5.23; extra == "complete"
Requires-Dist: pyopenssl>=23; extra == "complete"
Requires-Dist: redis~=4.3; extra == "complete"
Requires-Dist: s3fs<2024.7,>=2023.9.2; extra == "complete"
Requires-Dist: snowflake-connector-python~=3.7; extra == "complete"
Requires-Dist: sqlalchemy~=1.4; extra == "complete"
Requires-Dist: taos-ws-py==0.3.2; extra == "complete"
Provides-Extra: complete-api
Requires-Dist: adlfs==2023.9.0; extra == "complete-api"
Requires-Dist: aiobotocore<2.16,>=2.5.0; extra == "complete-api"
Requires-Dist: aiosmtplib~=3.0; extra == "complete-api"
Requires-Dist: alembic~=1.14; extra == "complete-api"
Requires-Dist: apscheduler<4,>=3.11; extra == "complete-api"
Requires-Dist: avro~=1.11; extra == "complete-api"
Requires-Dist: azure-core~=1.24; extra == "complete-api"
Requires-Dist: azure-identity~=1.5; extra == "complete-api"
Requires-Dist: azure-keyvault-secrets~=4.2; extra == "complete-api"
Requires-Dist: boto3<1.36,>=1.28.0; extra == "complete-api"
Requires-Dist: dask-kubernetes~=0.11.0; extra == "complete-api"
Requires-Dist: dask~=2023.12.1; python_version < "3.11" and extra == "complete-api"
Requires-Dist: dask~=2024.12.1; python_version >= "3.11" and extra == "complete-api"
Requires-Dist: databricks-sdk~=0.20.0; extra == "complete-api"
Requires-Dist: distributed~=2023.12.1; python_version < "3.11" and extra == "complete-api"
Requires-Dist: distributed~=2024.12.1; python_version >= "3.11" and extra == "complete-api"
Requires-Dist: fastapi~=0.115.6; extra == "complete-api"
Requires-Dist: gcsfs<2024.7,>=2023.9.2; extra == "complete-api"
Requires-Dist: google-cloud-bigquery-storage~=2.17; extra == "complete-api"
Requires-Dist: google-cloud-bigquery[bqstorage,pandas]==3.14.1; extra == "complete-api"
Requires-Dist: google-cloud-storage==2.14.0; extra == "complete-api"
Requires-Dist: google-cloud==0.34; extra == "complete-api"
Requires-Dist: graphviz~=0.20.0; extra == "complete-api"
Requires-Dist: grpcio~=1.70.0; extra == "complete-api"
Requires-Dist: humanfriendly~=10.0; extra == "complete-api"
Requires-Dist: igz-mgmt~=0.4.1; extra == "complete-api"
Requires-Dist: kafka-python~=2.1.0; extra == "complete-api"
Requires-Dist: memray~=1.12; sys_platform != "win32" and extra == "complete-api"
Requires-Dist: mlflow~=2.16; extra == "complete-api"
Requires-Dist: mlrun-pipelines-kfp-v1-8~=0.4.3; extra == "complete-api"
Requires-Dist: msrest~=0.6.21; extra == "complete-api"
Requires-Dist: objgraph~=3.6; extra == "complete-api"
Requires-Dist: oss2==2.18.1; extra == "complete-api"
Requires-Dist: ossfs==2023.12.0; extra == "complete-api"
Requires-Dist: plotly~=5.23; extra == "complete-api"
Requires-Dist: pydantic<2,>=1; extra == "complete-api"
Requires-Dist: pymysql~=1.1; extra == "complete-api"
Requires-Dist: pyopenssl>=23; extra == "complete-api"
Requires-Dist: redis~=4.3; extra == "complete-api"
Requires-Dist: s3fs<2024.7,>=2023.9.2; extra == "complete-api"
Requires-Dist: snowflake-connector-python~=3.7; extra == "complete-api"
Requires-Dist: sqlalchemy~=1.4; extra == "complete-api"
Requires-Dist: taos-ws-py==0.3.2; extra == "complete-api"
Requires-Dist: timelength~=1.1; extra == "complete-api"
Requires-Dist: uvicorn~=0.32.1; extra == "complete-api"
Dynamic: author
Dynamic: author-email
Dynamic: classifier
Dynamic: description
Dynamic: description-content-type
Dynamic: home-page
Dynamic: keywords
Dynamic: license
Dynamic: license-file
Dynamic: provides-extra
Dynamic: requires-dist
Dynamic: requires-python
Dynamic: summary
